README.md
setup.py
date_string/__init__.py
date_string/date_string.py
date_string.egg-info/PKG-INFO
date_string.egg-info/SOURCES.txt
date_string.egg-info/dependency_links.txt
date_string.egg-info/top_level.txt