Metadata-Version: 2.1
Name: date-string
Version: 0.2.1
Summary: Creates a manipulable date string in the form of 'YYYYmmdd'.
Home-page: UNKNOWN
Author: WeiJi Hsiao
License: MIT License
Platform: UNKNOWN
